PythonJiqirenXuexiShouceChuyi/README.md
PythonJiqirenXuexiShouceChuyi/__init__.py
PythonJiqirenXuexiShouceChuyi/__main__.py
PythonJiqirenXuexiShouceChuyi/file.epub
PythonJiqirenXuexiShouceChuyi/index.html
PythonJiqirenXuexiShouceChuyi/css/__init__.py
PythonJiqirenXuexiShouceChuyi/css/annotations.css
PythonJiqirenXuexiShouceChuyi/css/main.css
PythonJiqirenXuexiShouceChuyi/css/normalize.css
PythonJiqirenXuexiShouceChuyi/css/popup.css
PythonJiqirenXuexiShouceChuyi/font/__init__.py
PythonJiqirenXuexiShouceChuyi/font/fontello.eot
PythonJiqirenXuexiShouceChuyi/font/fontello.svg
PythonJiqirenXuexiShouceChuyi/font/fontello.ttf
PythonJiqirenXuexiShouceChuyi/font/fontello.woff
PythonJiqirenXuexiShouceChuyi/img/__init__.py
PythonJiqirenXuexiShouceChuyi/img/annotator-glyph-sprite.png
PythonJiqirenXuexiShouceChuyi/img/annotator-icon-sprite.png
PythonJiqirenXuexiShouceChuyi/img/apple-touch-icon.png
PythonJiqirenXuexiShouceChuyi/img/cancelfullscreen.png
PythonJiqirenXuexiShouceChuyi/img/close.png
PythonJiqirenXuexiShouceChuyi/img/fullscreen.png
PythonJiqirenXuexiShouceChuyi/img/loader.gif
PythonJiqirenXuexiShouceChuyi/img/menu-icon.png
PythonJiqirenXuexiShouceChuyi/img/save.png
PythonJiqirenXuexiShouceChuyi/img/saved.png
PythonJiqirenXuexiShouceChuyi/img/settings-s.png
PythonJiqirenXuexiShouceChuyi/img/settings.png
PythonJiqirenXuexiShouceChuyi/img/star.png
PythonJiqirenXuexiShouceChuyi/js/__init__.py
PythonJiqirenXuexiShouceChuyi/js/epub.js
PythonJiqirenXuexiShouceChuyi/js/epub.min.js
PythonJiqirenXuexiShouceChuyi/js/epub.min.map
PythonJiqirenXuexiShouceChuyi/js/hooks.min.js
PythonJiqirenXuexiShouceChuyi/js/hooks.min.map
PythonJiqirenXuexiShouceChuyi/js/reader.js
PythonJiqirenXuexiShouceChuyi/js/reader.js.map
PythonJiqirenXuexiShouceChuyi/js/reader.min.js
PythonJiqirenXuexiShouceChuyi/js/reader.min.map
PythonJiqirenXuexiShouceChuyi/js/hooks/__init__.py
PythonJiqirenXuexiShouceChuyi/js/hooks/extensions/__init__.py
PythonJiqirenXuexiShouceChuyi/js/hooks/extensions/highlight.js
python_jiqiren_xuexi_shouce_chuyi-2024.3.6.0.dist-info/METADATA
python_jiqiren_xuexi_shouce_chuyi-2024.3.6.0.dist-info/WHEEL
python_jiqiren_xuexi_shouce_chuyi-2024.3.6.0.dist-info/entry_points.txt
python_jiqiren_xuexi_shouce_chuyi-2024.3.6.0.dist-info/top_level.txt
python_jiqiren_xuexi_shouce_chuyi-2024.3.6.0.dist-info/RECORD
